gkdhighlight/__init__.py
gkdhighlight/impl.py
gkdhighlight-0.2.1.dist-info/LICENSE
gkdhighlight-0.2.1.dist-info/METADATA
gkdhighlight-0.2.1.dist-info/WHEEL
gkdhighlight-0.2.1.dist-info/entry_points.txt
gkdhighlight-0.2.1.dist-info/top_level.txt
gkdhighlight-0.2.1.dist-info/RECORD
