Metadata-Version: 2.1
Name: gkdhighlight
Version: 0.2.1
Summary: UNKNOWN
Home-page: https://github.com/thautwarm/gkdpygements
Author: thautwarm
Author-email: twshere@outlook.com
License: mit
Platform: any
Classifier: Programming Language :: Python :: 3.6
Classifier: Programming Language :: Python :: 3.7
Classifier: Programming Language :: Python :: 3.8
Classifier: Programming Language :: Python :: Implementation :: CPython
Requires-Python: >=3.6.0
Requires-Dist: pygments
Requires-Dist: gkdtex (<0.5,>=0.4)
